{"version":2,"thread":{"day":"2025-10-18","thread_id":"gransanger-sibirisk-ssp-tristis-900619","art":"Gransanger, Sibirisk (ssp. tristis)","lok":"Gjerrild Nordstrand øst, Knudshoved","loknr":"900619","region":"DOF Østjylland","coords":null,"first_ts_obs":"2025-10-18T00:00:00+02:00","last_ts_obs":"2025-10-18T00:00:00+02:00","last_active_ts_obs":null,"last_kategori":"sub","status":"active","max_antal_num":0.0,"last_antal_num":0.0,"num_events":1,"has_nonzero_today":false,"last_adf":"Rastende","last_observer":"Jørgen Staarup Christensen"},"events":[{"event_type":"obs","obsid":"37866128","art":"Gransanger, Sibirisk (ssp. tristis)","lok":"Gjerrild Nordstrand øst, Knudshoved","loknr":"900619","region":"DOF Østjylland","antal_num":0.0,"antal_text":"0","kategori":"sub","adf":"Rastende","observer":"Jørgen Staarup Christensen","ts_obs":"2025-10-18T00:00:00+02:00","ts_seen":"2025-10-18T23:59:30.463963+02:00","turnoter":"Strø-obs, mest fra sommerhus-have","fuglnoter":"Helt brun gransanger, men desværre lydløs.","raw":{"Dato":"2025-10-18","Turtidfra":"","Turtidtil":"","Loknr":"900619","Loknavn":"Gjerrild Nordstrand øst, Knudshoved","Artnr":"13113","Artnavn":"Gransanger, Sibirisk (ssp. tristis)","Latin":"Phylloscopus collybita tristis","Sortering":"6330","Antal":"0","Koen":"-","Adfkode":"R","Adfbeskrivelse":"Rastende","Alderkode":"-","Dragtkode":"-","Dragtbeskrivelse":"Uspecificeret dragt","Obserkode":"8230JSC","Fornavn":"Jørgen Staarup","Efternavn":"Christensen","Obser_by":"Åbyhøj","Medobser":"","Turnoter":"Strø-obs, mest fra sommerhus-have","Fuglnoter":"Helt brun gransanger, men desværre lydløs.","Metode":"Uspecificeret/tilfældig","Obstidfra":"","Obstidtil":"","Hemmelig":"0","Kvalitet":"1","Turid":"5883189","Obsid":"37866128","DOF_afdeling":"DOF Østjylland","lok_laengdegrad":"10,82412470101604","lok_breddegrad":"56,53158580574126","obs_laengdegrad":"","obs_breddegrad":"","radius":"","obser_laengdegrad":"","obser_breddegrad":"","group_key":"Gransanger, Sibirisk (ssp. tristis)\n900619","_antal_num":0.0,"kategori":"sub"}}],"stats":{"num_events":1,"max_antal_num":0.0,"max_antal_ts_obs":"2025-10-18T00:00:00+02:00"}}