{"version":2,"thread":{"day":"2025-10-19","thread_id":"soekonge-785013","art":"Søkonge","lok":"Agger Tange, havsiden","loknr":"785013","region":"DOF Nordvestjylland","coords":null,"first_ts_obs":"2025-10-19T00:00:00+02:00","last_ts_obs":"2025-10-19T00:00:00+02:00","last_active_ts_obs":"2025-10-19T00:00:00+02:00","last_kategori":"sub","status":"active","max_antal_num":1.0,"last_antal_num":1.0,"num_events":2,"has_nonzero_today":true,"last_adf":"Fouragerende","last_observer":"Henrik Toft"},"events":[{"event_type":"obs","obsid":"37873549","art":"Søkonge","lok":"Agger Tange, havsiden","loknr":"785013","region":"DOF Nordvestjylland","antal_num":1.0,"antal_text":"1","kategori":"sub","adf":"Fouragerende","observer":"Henrik Toft","ts_obs":"2025-10-19T00:00:00+02:00","ts_seen":"2025-10-19T22:13:07.520599+02:00","fuglnoter":"Lange mole","raw":{"Dato":"2025-10-19","Turtidfra":"","Turtidtil":"","Loknr":"785013","Loknavn":"Agger Tange, havsiden","Artnr":"06470","Artnavn":"Søkonge","Latin":"Alle alle","Sortering":"3000","Antal":"1","Koen":"-","Adfkode":"FU","Adfbeskrivelse":"Fouragerende","Alderkode":"-","Dragtkode":"-","Dragtbeskrivelse":"Uspecificeret dragt","Obserkode":"7400HT","Fornavn":"Henrik","Efternavn":"Toft","Obser_by":"Herning","Medobser":"","Turnoter":"","Fuglnoter":"Lange mole","Metode":"Uspecificeret/tilfældig","Obstidfra":"","Obstidtil":"","Hemmelig":"0","Kvalitet":"1","Turid":"5884661","Obsid":"37873549","DOF_afdeling":"DOF Nordvestjylland","lok_laengdegrad":"8,21652339120534","lok_breddegrad":"56,74663689042774","obs_laengdegrad":"","obs_breddegrad":"","radius":"","obser_laengdegrad":"","obser_breddegrad":"","group_key":"Søkonge\n785013","_antal_num":1.0,"kategori":"sub"}},{"event_type":"obs","obsid":"37874455","art":"Søkonge","lok":"Agger Tange, havsiden","loknr":"785013","region":"DOF Nordvestjylland","antal_num":1.0,"antal_text":"1","kategori":"sub","adf":"Fouragerende","observer":"Sten Nielsen","ts_obs":"2025-10-19T00:00:00+02:00","ts_seen":"2025-10-19T22:13:07.521599+02:00","fuglnoter":"Langs nordsiden af Lange Mole","raw":{"Dato":"2025-10-19","Turtidfra":"","Turtidtil":"","Loknr":"785013","Loknavn":"Agger Tange, havsiden","Artnr":"06470","Artnavn":"Søkonge","Latin":"Alle alle","Sortering":"3000","Antal":"1","Koen":"-","Adfkode":"FU","Adfbeskrivelse":"Fouragerende","Alderkode":"-","Dragtkode":"-","Dragtbeskrivelse":"Uspecificeret dragt","Obserkode":"6040SN","Fornavn":"Sten","Efternavn":"Nielsen","Obser_by":"Vestervig","Medobser":"","Turnoter":"","Fuglnoter":"Langs nordsiden af Lange Mole","Metode":"Uspecificeret/tilfældig","Obstidfra":"","Obstidtil":"","Hemmelig":"0","Kvalitet":"1","Turid":"5884788","Obsid":"37874455","DOF_afdeling":"DOF Nordvestjylland","lok_laengdegrad":"8,21652339120534","lok_breddegrad":"56,74663689042774","obs_laengdegrad":"8,215980174368978","obs_breddegrad":"56,72308570917209","radius":"50","obser_laengdegrad":"","obser_breddegrad":"","group_key":"Søkonge\n785013","_antal_num":1.0,"kategori":"sub"}}],"stats":{"num_events":2,"max_antal_num":1.0,"max_antal_ts_obs":"2025-10-19T00:00:00+02:00"}}