{
"client": "alm-nordsjaelland",
"count": 3,
"generated": "2025-10-18T16:57:46.488728+02:00",
"items": [
{
"obsid": "37864107",
"art": "Blå Kærhøg",
"antal": "2",
"adf": "Trækkende mod sydvest",
"lok": "Skansebakken",
"dof_afdeling": "DOF Nordsjælland",
"fornavn": "Per",
"efternavn": "Ekberg",
"lon": "12,337238432313955",
"lat": "55,93525313453108",
"tid_fra": "09:00",
"tid_til": "16:30",
"kategori": "bemaerk"
},
{
"obsid": "37864110",
"art": "Spurvehøg",
"antal": "38",
"adf": "Trækkende mod sydvest",
"lok": "Skansebakken",
"dof_afdeling": "DOF Nordsjælland",
"fornavn": "Per",
"efternavn": "Ekberg",
"lon": "12,337238432313955",
"lat": "55,93525313453108",
"tid_fra": "09:00",
"tid_til": "16:30",
"kategori": "bemaerk"
},
{
"obsid": "37864116",
"art": "Musvåge",
"antal": "592",
"adf": "Trækkende mod sydvest",
"lok": "Skansebakken",
"dof_afdeling": "DOF Nordsjælland",
"fornavn": "Per",
"efternavn": "Ekberg",
"lon": "12,337238432313955",
"lat": "55,93525313453108",
"tid_fra": "09:00",
"tid_til": "16:30",
"kategori": "bemaerk"
}
]
}