{
"client": "alm-bornholm",
"count": 2,
"generated": "2025-10-14T16:20:52.911551+02:00",
"items": [
{
"obsid": "37835300",
"art": "Krikand",
"antal": "140",
"adf": "Rastende",
"lok": "Udkæret",
"dof_afdeling": "DOF Bornholm",
"fornavn": "Steen E.",
"efternavn": "Jensen",
"lon": "14,86989194977544",
"lat": "55,09941246833165",
"tid_fra": "13:25",
"tid_til": "14:05",
"kategori": "bemaerk"
},
{
"obsid": "37835305",
"art": "Sortstrubet Bynkefugl",
"antal": "2",
"adf": "Rastende",
"lok": "Udkæret",
"dof_afdeling": "DOF Bornholm",
"fornavn": "Steen E.",
"efternavn": "Jensen",
"lon": "14,86989194977544",
"lat": "55,09941246833165",
"tid_fra": "13:25",
"tid_til": "14:05",
"kategori": "bemaerk"
}
]
}